{"cameraMode":{"drawMode":0,"name":"Shaded","section":"Shading Mode"},"sceneLighting":true,"audioPlay":false,"sceneViewState":{"m_AlwaysRefresh":false,"showFog":true,"showSkybox":true,"showFlares":true,"showImageEffects":true,"showParticleSystems":true,"showVisualEffectGraphs":true,"m_FxEnabled":true},"in2DMode":false,"pivot":{"x":4.078118801116943,"y":0.29795145988464358,"z":1.297353744506836},"rotation":{"x":-0.32928338646888735,"y":-0.15289825201034547,"z":0.05410446599125862,"w":-0.9302425384521484},"size":10.036238670349121,"orthographic":false}